alibabacloud_lingmou20250527/__init__.py
alibabacloud_lingmou20250527/client.py
alibabacloud_lingmou20250527/models/__init__.py
alibabacloud_lingmou20250527/models/_broadcast_template.py
alibabacloud_lingmou20250527/models/_broadcast_video.py
alibabacloud_lingmou20250527/models/_chat_session_info.py
alibabacloud_lingmou20250527/models/_close_chat_instance_sessions_request.py
alibabacloud_lingmou20250527/models/_close_chat_instance_sessions_response.py
alibabacloud_lingmou20250527/models/_close_chat_instance_sessions_response_body.py
alibabacloud_lingmou20250527/models/_close_chat_instance_sessions_shrink_request.py
alibabacloud_lingmou20250527/models/_confirm_train_pic_avatar_request.py
alibabacloud_lingmou20250527/models/_confirm_train_pic_avatar_response.py
alibabacloud_lingmou20250527/models/_confirm_train_pic_avatar_response_body.py
alibabacloud_lingmou20250527/models/_create_background_pic_request.py
alibabacloud_lingmou20250527/models/_create_background_pic_response.py
alibabacloud_lingmou20250527/models/_create_background_pic_response_body.py
alibabacloud_lingmou20250527/models/_create_broadcast_sticker_request.py
alibabacloud_lingmou20250527/models/_create_broadcast_sticker_response.py
alibabacloud_lingmou20250527/models/_create_broadcast_sticker_response_body.py
alibabacloud_lingmou20250527/models/_create_broadcast_video_from_template_request.py
alibabacloud_lingmou20250527/models/_create_broadcast_video_from_template_response.py
alibabacloud_lingmou20250527/models/_create_broadcast_video_from_template_response_body.py
alibabacloud_lingmou20250527/models/_create_chat_config_request.py
alibabacloud_lingmou20250527/models/_create_chat_config_response.py
alibabacloud_lingmou20250527/models/_create_chat_config_response_body.py
alibabacloud_lingmou20250527/models/_create_chat_session_request.py
alibabacloud_lingmou20250527/models/_create_chat_session_response.py
alibabacloud_lingmou20250527/models/_create_chat_session_response_body.py
alibabacloud_lingmou20250527-1.5.3.dist-info/LICENSE
alibabacloud_lingmou20250527-1.5.3.dist-info/METADATA
alibabacloud_lingmou20250527-1.5.3.dist-info/WHEEL
alibabacloud_lingmou20250527-1.5.3.dist-info/top_level.txt
alibabacloud_lingmou20250527-1.5.3.dist-info/RECORD
